EasyMenu/__init__.py
EasyMenu/menu.py
EasyMenu/menu_nocolor.py
EasyMenu-0.3.2.dist-info/LICENSE
EasyMenu-0.3.2.dist-info/METADATA
EasyMenu-0.3.2.dist-info/WHEEL
EasyMenu-0.3.2.dist-info/top_level.txt
EasyMenu-0.3.2.dist-info/RECORD
