Metadata-Version: 2.1
Name: EasyMenu
Version: 0.3.2
Summary: Uma biblioteca feita para facilitar o desenvolvimento de menu interativo no Python 3.6.x
Home-page: https://github.com/nvrsantos/easymenu.py
Author: nevr001, KevinAp-5
Author-email: nvrsantos@users.noreply.github.com
License: MIT License
Keywords: menu easy menu_Python python_3.6.x
Platform: UNKNOWN
Classifier: Development Status :: 3 - Alpha
Classifier: Topic :: Software Development :: Build Tools
Classifier: License :: OSI Approved :: MIT License
Classifier: Programming Language :: Python :: 3
Classifier: Programming Language :: Python :: 3.6
Classifier: Programming Language :: Python :: 3.7
Classifier: Programming Language :: Python :: 3.8
Requires-Python: >=3.6
Requires-Dist: colorama
